Metadata-Version: 2.1
Name: mapdamage
Version: 2.2.3
Summary: mapDamage tracks and quantifies DNA damage patterns in ancient DNA sequencing reads generated by Next-Generation Sequencing platforms
Author: Aurélien Ginolhac, Mikkel Schubert, Hákon Jónsson
License: MIT
Project-URL: Homepage, https://github.com/ginolhac/mapDamage
Project-URL: Documentation, https://ginolhac.github.io/mapDamage/
Project-URL: Repository, https://github.com/ginolhac/mapDamage.git
Project-URL: Issues, https://github.com/ginolhac/mapDamage/issues
Classifier: Development Status :: 5 - Production/Stable
Classifier: Intended Audience :: Science/Research
Classifier: Topic :: Scientific/Engineering :: Bio-Informatics
Classifier: Programming Language :: Python :: 3 :: Only
Classifier: Programming Language :: Python :: 3.7
Classifier: Programming Language :: Python :: 3.8
Classifier: Programming Language :: Python :: 3.9
Classifier: Programming Language :: Python :: 3.10
Classifier: Programming Language :: Python :: 3.11
Classifier: Programming Language :: Python :: 3.12
Classifier: Programming Language :: Python :: 3.13
Requires-Python: >=3.7
License-File: LICENSE.txt
